odoo/addons/mail_gateway_whatsapp/README.rst
odoo/addons/mail_gateway_whatsapp/__init__.py
odoo/addons/mail_gateway_whatsapp/__manifest__.py
odoo/addons/mail_gateway_whatsapp/i18n/es.po
odoo/addons/mail_gateway_whatsapp/i18n/it.po
odoo/addons/mail_gateway_whatsapp/i18n/mail_gateway_whatsapp.pot
odoo/addons/mail_gateway_whatsapp/models/__init__.py
odoo/addons/mail_gateway_whatsapp/models/discuss_channel.py
odoo/addons/mail_gateway_whatsapp/models/mail_gateway.py
odoo/addons/mail_gateway_whatsapp/models/mail_gateway_whatsapp.py
odoo/addons/mail_gateway_whatsapp/models/mail_thread.py
odoo/addons/mail_gateway_whatsapp/models/mail_whatsapp_template.py
odoo/addons/mail_gateway_whatsapp/models/res_partner.py
odoo/addons/mail_gateway_whatsapp/readme/CONFIGURE.md
odoo/addons/mail_gateway_whatsapp/readme/CONTRIBUTORS.md
odoo/addons/mail_gateway_whatsapp/readme/CREDITS.md
odoo/addons/mail_gateway_whatsapp/readme/DESCRIPTION.md
odoo/addons/mail_gateway_whatsapp/readme/ROADMAP.md
odoo/addons/mail_gateway_whatsapp/readme/USAGE.md
odoo/addons/mail_gateway_whatsapp/security/ir.model.access.csv
odoo/addons/mail_gateway_whatsapp/security/security.xml
odoo/addons/mail_gateway_whatsapp/static/description/icon.png
odoo/addons/mail_gateway_whatsapp/static/description/icon.svg
odoo/addons/mail_gateway_whatsapp/static/description/index.html
odoo/addons/mail_gateway_whatsapp/static/src/components/message/message.xml
odoo/addons/mail_gateway_whatsapp/static/src/components/message/message_patch.esm.js
odoo/addons/mail_gateway_whatsapp/static/src/components/phone_field/phone_field.esm.js
odoo/addons/mail_gateway_whatsapp/static/src/components/phone_field/phone_field.xml
odoo/addons/mail_gateway_whatsapp/static/src/components/send_whatsapp_button/send_whatsapp_button.esm.js
odoo/addons/mail_gateway_whatsapp/static/src/components/send_whatsapp_button/send_whatsapp_button.xml
odoo/addons/mail_gateway_whatsapp/tests/__init__.py
odoo/addons/mail_gateway_whatsapp/tests/test_mail_gateway_whatsapp.py
odoo_addon_mail_gateway_whatsapp-17.0.1.0.1.dist-info/METADATA
odoo_addon_mail_gateway_whatsapp-17.0.1.0.1.dist-info/WHEEL
odoo_addon_mail_gateway_whatsapp-17.0.1.0.1.dist-info/top_level.txt
odoo_addon_mail_gateway_whatsapp-17.0.1.0.1.dist-info/RECORD
