Metadata-Version: 2.1
Name: odoo-addon-mail_gateway_whatsapp
Version: 17.0.1.0.1
Requires-Python: >=3.10
Requires-Dist: odoo-addon-mail_gateway>=17.0dev,<17.1dev
Requires-Dist: odoo>=17.0a,<17.1dev
Requires-Dist: requests_toolbelt
Summary: Set a gateway for whatsapp
Home-page: https://github.com/OCA/social
License: AGPL-3
Author: Creu Blanca, Dixmit, Odoo Community Association (OCA)
Author-email: support@odoo-community.org
Classifier: Programming Language :: Python
Classifier: Framework :: Odoo
Classifier: Framework :: Odoo :: 17.0
Classifier: License :: OSI Approved :: GNU Affero General Public License v3
